code_scanner/__init__.py
code_scanner/code_scanner.py
code_scanner-0.1.1.dist-info/LICENSE
code_scanner-0.1.1.dist-info/METADATA
code_scanner-0.1.1.dist-info/WHEEL
code_scanner-0.1.1.dist-info/entry_points.txt
code_scanner-0.1.1.dist-info/top_level.txt
code_scanner-0.1.1.dist-info/RECORD
