Metadata-Version: 2.1
Name: code-scanner
Version: 0.1.1
Summary: A simple code scanner tool
Home-page: https://github.com/matahariramadhan/code-scanner
Author: Matahari Ramadhan
Author-email: ramadhan.matahari24@gmail.com
Classifier: Programming Language :: Python :: 3
Classifier: License :: OSI Approved :: MIT License
Classifier: Operating System :: OS Independent
Requires-Python: >=3.6
License-File: LICENSE
